{"content":[{"id":"faq-accordion","heading":{"short":"Frequently Asked Questions","medium":"Common questions about Cashvers and earning online."},"sentence":{"short":"Get answers to your questions.","medium":"Learn how Cashvers works and how you can benefit."},"overline":{"short":"Your Queries Answered"},"button":{"short":"Learn More"},"accordion":[{"title-medium":"What is Cashvers?","paragraph-medium":"Cashvers is an online platform where users earn rewards by completing tasks like surveys and playing games."},{"title-medium":"How can I earn money?","paragraph-medium":"You can earn money by participating in paid surveys, playing games, and testing applications on our platform."},{"title-medium":"Is Cashvers safe to use?","paragraph-medium":"Yes, Cashvers prioritizes user safety with robust fraud protection and secure payment methods."},{"title-medium":"What types of rewards are offered?","paragraph-medium":"Users can earn cash, gift cards, and in-game currencies through various online activities."},{"title-medium":"How fast can I receive my rewards?","paragraph-medium":"Rewards are processed quickly, ensuring you get your earnings in a timely manner."}]}]}